raysim/__init__.py
raysim/agents/__init__.py
raysim/agents/base_agent.py
raysim/agents/base_state.py
raysim/agents/funds_agent.py
raysim/agents/utils.py
raysim/mutable_fields/__init__.py
raysim/mutable_fields/agent_set.py
raysim/mutable_fields/base.py
raysim/simulation/__init__.py
raysim/simulation/management.py
raysim/simulation/orchestrating.py
raysim/updating/__init__.py
raysim/updating/base.py
raysim/updating/basic_updates.py
raysim/updating/updates.py
raysim-0.1.0.dist-info/licenses/LICENSE
raysim-0.1.0.dist-info/METADATA
raysim-0.1.0.dist-info/WHEEL
raysim-0.1.0.dist-info/top_level.txt
raysim-0.1.0.dist-info/RECORD
