Metadata-Version: 2.4
Name: raysim
Version: 0.1.0
Summary: A distributed simulation framework using Ray.
Author-email: Harry Chen <harrychen0805@outlook.com>
Project-URL: Homepage, https://github.com/harry0805/raysim
Project-URL: Bug Tracker, https://github.com/harry0805/raysim/issues
Requires-Python: >=3.12
License-File: LICENSE
Requires-Dist: ray[default]
Requires-Dist: tqdm
Dynamic: license-file
